{"1.2358798806784053e-05": {}, "0.00121421689826281": {"Bacteroides_caecimuris_I48": {"Internal Flux Below 0": ["rxn05319_c0"], "Constraint Violated": []}}, "0.0727703507700821": {}, "0.08217035503961416": {"Bacteroides_caecimuris_I48": {"Internal Flux Below 0": ["rxn00184_c0"], "Constraint Violated": []}}, "0.09872406619575476": {"Bacteroides_caecimuris_I48": {"Internal Flux Below 0": [], "Constraint Violated": ["L-Serine exchange upper bound"]}}, "0.09877204281488944": {}, "0.10461631224736405": {"Bacteroides_caecimuris_I48": {"Internal Flux Below 0": ["rxn00799_c0"], "Constraint Violated": []}}, "0.10461679786189251": {}, "0.20402866990999025": {"Bacteroides_caecimuris_I48": {"Internal Flux Below 0": [], "Constraint Violated": ["L-Aspartate-e0 exchange upper bound"]}}, "0.2040905979007762": {}, "0.20418732454212926": {"Bacteroides_caecimuris_I48": {"Internal Flux Below 0": ["rxn00709_c0"], "Constraint Violated": []}}, "0.20429701555971286": {}, "0.21088119290863983": {}, "0.2117895776703365": {"Bacteroides_caecimuris_I48": {"Internal Flux Below 0": ["rxn08661_c0"], "Constraint Violated": []}}, "0.2367144168853486": {}, "0.2420303755172218": {}, "0.24203572550381983": {"Bacteroides_caecimuris_I48": {"Internal Flux Below 0": ["rxn00693_c0"], "Constraint Violated": []}}, "0.24203840051872502": {}, "0.2420772113726241": {"Bacteroides_caecimuris_I48": {"Internal Flux Below 0": ["rxn00692_c0_R"], "Constraint Violated": []}}, "6.4287365591137435": {}}