{"9.991443067300677e-07": {}, "1.235876028324364e-05": {}, "3.6597670802015153e-05": {"Muribaculum_intestinale_YL27": {"Internal Flux Below 0": ["rxn00555_c0_R"], "Constraint Violated": []}}, "0.0005178818520457063": {}, "0.0005931358860326231": {"Limosilactobacillus_reuteri_I49": {"Internal Flux Below 0": ["rxn08661_c0_R"], "Constraint Violated": []}}, "0.0006563662760544956": {}, "0.0008582950053110282": {"Enterococcus_faecalis_KB1": {"Internal Flux Below 0": ["rxn00551_c0"], "Constraint Violated": []}}, "0.0008585805824470423": {}, "0.0008705082803601371": {"Clostridium_innocuum_I46": {"Internal Flux Below 0": ["rxn00182_c0_R"], "Constraint Violated": []}}, "0.0010015458884904914": {}, "0.0012073774017706802": {"Bacteroides_caecimuris_I48": {"Internal Flux Below 0": ["rxn05319_c0"], "Constraint Violated": []}}, "0.001423803178756869": {"Clostridium_innocuum_I46": {"Internal Flux Below 0": ["rxn00148_c0_R"], "Constraint Violated": []}}, "0.0015075159252109925": {}, "0.0020372202366657297": {"Flavonifractor_plautii_YL31": {"Internal Flux Below 0": ["rxn05887_c0_R"], "Constraint Violated": []}}, "0.0021962980113581694": {}, "0.0028922140229421904": {}, "0.0032333762095908053": {"Clostridium_innocuum_I46": {"Internal Flux Below 0": ["rxn05938_c0_R"], "Constraint Violated": []}}, "0.0032350351761705185": {"Clostridium_innocuum_I46": {"Internal Flux Below 0": ["rxn00787_c0"], "Constraint Violated": []}}, "0.0033237068711036107": {}, "0.0034700742664229532": {}, "0.003982205683494805": {"Clostridium_innocuum_I46": {"Internal Flux Below 0": ["rxn08168_c0"], "Constraint Violated": []}}, "0.00502921541091739": {"Clostridium_innocuum_I46": {"Internal Flux Below 0": ["rxn05496_c0_R"], "Constraint Violated": []}}, "0.005289335207205172": {"Clostridium_innocuum_I46": {"Internal Flux Below 0": ["rxn04793_c0"], "Constraint Violated": []}}, "0.005728431693488078": {}, "0.005820716767985718": {}, "0.006647487568029279": {}, "0.006931739185870129": {}, "0.008194302849363684": {}, "0.008286507847541074": {}, "0.008372698309079534": {}, "0.008489068095725581": {}, "0.009050106990622522": {}, "0.009089593777810729": {}, "0.009721442645523309": {}, "0.010536448435126971": {}, "0.011196025969676714": {}, "0.011720569414017315": {}, "0.01199777688898365": {}, "0.011998492105713535": {"Limosilactobacillus_reuteri_I49": {"Internal Flux Below 0": ["rxn90015_c0"], "Constraint Violated": []}}, "0.012007946374939502": {"Limosilactobacillus_reuteri_I49": {"Internal Flux Below 0": ["rxn00692_c0_R"], "Constraint Violated": []}}, "0.01211819013547884": {"Limosilactobacillus_reuteri_I49": {"Internal Flux Below 0": ["rxn09247_c0"], "Constraint Violated": []}}, "0.012122052363695667": {"Limosilactobacillus_reuteri_I49": {"Internal Flux Below 0": ["rxn05618_c0"], "Constraint Violated": []}}, "0.012125504522339287": {"Limosilactobacillus_reuteri_I49": {"Internal Flux Below 0": ["rxn00615_c0"], "Constraint Violated": []}}, "0.012129366735751634": {}, "0.01213322891844857": {}, "0.012789181285031634": {"Limosilactobacillus_reuteri_I49": {"Internal Flux Below 0": ["rxn00346_c0"], "Constraint Violated": []}}, "0.012820247464603834": {"Limosilactobacillus_reuteri_I49": {"Internal Flux Below 0": ["rxn05217_c0"], "Constraint Violated": []}}, "0.01306170795989801": {"Akkermansia_muciniphilaYL44": {"Internal Flux Below 0": ["rxn08173_c0"], "Constraint Violated": []}}, "0.025343545509968174": {"Flavonifractor_plautii_YL31": {"Internal Flux Below 0": ["rxn05938_c0_R"], "Constraint Violated": []}}}